cdklabs/genai_idp_bda_processor/__init__.py
cdklabs/genai_idp_bda_processor/py.typed
cdklabs/genai_idp_bda_processor/_jsii/__init__.py
cdklabs/genai_idp_bda_processor/_jsii/genai-idp-bda-processor@0.0.1.jsii.tgz
cdklabs_genai_idp_bda_processor-0.0.1.dist-info/LICENSE
cdklabs_genai_idp_bda_processor-0.0.1.dist-info/METADATA
cdklabs_genai_idp_bda_processor-0.0.1.dist-info/WHEEL
cdklabs_genai_idp_bda_processor-0.0.1.dist-info/top_level.txt
cdklabs_genai_idp_bda_processor-0.0.1.dist-info/RECORD
