Metadata-Version: 2.1
Name: cdklabs.genai-idp-bda-processor
Version: 0.0.1
Summary: @cdklabs/genai-idp-bda-processor
Home-page: https://github.com/cdklabs/genai-idp
Author: AWS<aws-cdk-dev@amazon.com>
License: Apache-2.0
Project-URL: Source, https://github.com/cdklabs/genai-idp
Classifier: Intended Audience :: Developers
Classifier: Operating System :: OS Independent
Classifier: Programming Language :: JavaScript
Classifier: Programming Language :: Python :: 3 :: Only
Classifier: Programming Language :: Python :: 3.9
Classifier: Programming Language :: Python :: 3.10
Classifier: Programming Language :: Python :: 3.11
Classifier: Typing :: Typed
Classifier: Development Status :: 4 - Beta
Classifier: License :: OSI Approved
Requires-Python: ~=3.9
License-File: LICENSE
Requires-Dist: aws-cdk-lib <3.0.0,>=2.214.0
Requires-Dist: aws-cdk.aws-glue-alpha <3.0.0,>=2.214.0.a0
Requires-Dist: aws-cdk.aws-lambda-python-alpha <3.0.0,>=2.214.0.a0
Requires-Dist: aws-cdk.aws-sagemaker-alpha <3.0.0,>=2.214.0.a0
Requires-Dist: cdklabs.genai-idp <0.0.2,>=0.0.1
Requires-Dist: cdklabs.generative-ai-cdk-constructs <0.2.0,>=0.1.309
Requires-Dist: constructs <11.0.0,>=10.4.2
Requires-Dist: jsii <2.0.0,>=1.114.1
Requires-Dist: publication >=0.0.3
Requires-Dist: typeguard <4.3.0,>=2.13.3
